sk/linearregression/HandleMissingValue.py
sk/linearregression/LinearRegression.py
sk/linearregression/MinMaxScaler.py
sk/linearregression/TrainTestSplit.py
sk/linearregression/__init__.py
sk_linearregression-0.4.0.dist-info/METADATA
sk_linearregression-0.4.0.dist-info/WHEEL
sk_linearregression-0.4.0.dist-info/RECORD
