Metadata-Version: 2.4
Name: sk-linearregression
Version: 0.4.0
Summary: My own Linear Regression under the sk.* namespace
Author-email: Shahabaj Khan <shahabaj773@gmail.com>
Requires-Python: >=3.8
